nbsysinfo/__init__.py
nbsysinfo/etc/nbext_sysinfo.json
nbsysinfo/etc/server_sysinfo.json
nbsysinfo/static/main.js
nbsysinfo/static/tree.css
nbsysinfo-0.1.5.data/data/etc/jupyter/jupyter_notebook_config.d/server_sysinfo.json
nbsysinfo-0.1.5.data/data/etc/jupyter/nbconfig/notebook.d/nbext_sysinfo.json
nbsysinfo-0.1.5.data/data/share/jupyter/nbextensions/nbsysinfo/main.js
nbsysinfo-0.1.5.data/data/share/jupyter/nbextensions/nbsysinfo/tree.css
nbsysinfo-0.1.5.dist-info/METADATA
nbsysinfo-0.1.5.dist-info/WHEEL
nbsysinfo-0.1.5.dist-info/top_level.txt
nbsysinfo-0.1.5.dist-info/RECORD
